SLMlayout/__init__.py
SLMlayout/core.py
SLMlayout/functions.py
SLMlayout/numba_functions.py
SLMlayout/layouts/__init__.py
SLMlayout/layouts/hexagons.py
SLMlayout/layouts/squares.py
SLMlayout-0.3.1.dist-info/LICENSE
SLMlayout-0.3.1.dist-info/METADATA
SLMlayout-0.3.1.dist-info/WHEEL
SLMlayout-0.3.1.dist-info/top_level.txt
SLMlayout-0.3.1.dist-info/RECORD
