Metadata-Version: 2.1
Name: SLMlayout
Version: 0.3.1
Summary: UNKNOWN
Home-page: UNKNOWN
Author: UNKNOWN
Author-email: UNKNOWN
License: UNKNOWN
Platform: UNKNOWN
Requires-Dist: numpy
Requires-Dist: matplotlib
Requires-Dist: sphinx
Requires-Dist: sphinx-rtd-theme
Requires-Dist: numba
